django_salted_api_tokens/__init__.py
django_salted_api_tokens/admin.py
django_salted_api_tokens/authentication.py
django_salted_api_tokens/models.py
django_salted_api_tokens/serializers.py
django_salted_api_tokens/settings.py
django_salted_api_tokens/urls.py
django_salted_api_tokens/utils.py
django_salted_api_tokens/views.py
django_salted_api_tokens/management/__init__.py
django_salted_api_tokens/management/commands/__init__.py
django_salted_api_tokens/management/commands/create_dsat_for_user.py
django_salted_api_tokens/migrations/0001_initial.py
django_salted_api_tokens/migrations/__init__.py
example_django_project/__init__.py
example_django_project/manage.py
example_django_project/accounts/__init__.py
example_django_project/accounts/admin.py
example_django_project/accounts/apps.py
example_django_project/accounts/models.py
example_django_project/accounts/tests.py
example_django_project/accounts/urls.py
example_django_project/accounts/views.py
example_django_project/accounts/migrations/__init__.py
example_django_project/example_django_project/__init__.py
example_django_project/example_django_project/settings.py
example_django_project/example_django_project/urls.py
example_django_project/example_django_project/wsgi.py
tests/__init__.py
tests/factories.py
tests/test_authentication_api_key_secret.py
tests/test_mgmt_cmd_create_dsat_for_user.py
tests/test_view_create_api_key_secret.py
django_salted_api_tokens-1.0.3.dist-info/LICENSE
django_salted_api_tokens-1.0.3.dist-info/METADATA
django_salted_api_tokens-1.0.3.dist-info/WHEEL
django_salted_api_tokens-1.0.3.dist-info/top_level.txt
django_salted_api_tokens-1.0.3.dist-info/RECORD
