Metadata-Version: 2.1
Name: django-salted-api-tokens
Version: 1.0.3
Summary: Django token authentication with hashed, salted tokens
Author-email: Harisankar Krishna Swamy <harisankar.krishna@outlook.com>
Project-URL: Homepage, https://github.com/harisankar-krishna-swamy/django_salted_api_tokens
Classifier: Programming Language :: Python :: 3
Classifier: License :: OSI Approved :: Apache Software License
Classifier: Operating System :: OS Independent
Requires-Python: >=3.9.2
License-File: LICENSE
Requires-Dist: Django (>=3.2.18)
Requires-Dist: djangorestframework (>=3.12.4)
Requires-Dist: ksuid (>=1.3)
